donation_alerts_handler/donation_alerts.py
donation_alerts_handler/filters.py
donation_alerts_handler/types/custom_alert.py
donation_alerts_handler/types/donations.py
donation_alerts_handler/types/merchandise.py
donation_alerts_handler/types/merchandise_sale.py
donation_alerts_handler/types/user_profile.py
DonationAlertsHandler-1.1.dist-info/METADATA
DonationAlertsHandler-1.1.dist-info/WHEEL
DonationAlertsHandler-1.1.dist-info/top_level.txt
DonationAlertsHandler-1.1.dist-info/RECORD
